declearn/__init__.py
declearn/py.typed
declearn/typing.py
declearn/version.py
declearn/aggregator/__init__.py
declearn/aggregator/_api.py
declearn/aggregator/_avg.py
declearn/aggregator/_gma.py
declearn/aggregator/_sum.py
declearn/communication/__init__.py
declearn/communication/api/__init__.py
declearn/communication/api/_client.py
declearn/communication/api/_server.py
declearn/communication/api/backend/__init__.py
declearn/communication/api/backend/_handler.py
declearn/communication/api/backend/actions.py
declearn/communication/api/backend/flags.py
declearn/communication/grpc/__init__.py
declearn/communication/grpc/_client.py
declearn/communication/grpc/_server.py
declearn/communication/grpc/protobufs/__init__.py
declearn/communication/grpc/protobufs/message.proto
declearn/communication/grpc/protobufs/message_pb2.py
declearn/communication/grpc/protobufs/message_pb2_grpc.py
declearn/communication/utils/__init__.py
declearn/communication/utils/_build.py
declearn/communication/utils/_parse.py
declearn/communication/websockets/__init__.py
declearn/communication/websockets/_client.py
declearn/communication/websockets/_server.py
declearn/communication/websockets/_tools.py
declearn/data_info/__init__.py
declearn/data_info/_base.py
declearn/data_info/_fields.py
declearn/dataset/__init__.py
declearn/dataset/_base.py
declearn/dataset/_inmemory.py
declearn/dataset/_split_data.py
declearn/dataset/examples/__init__.py
declearn/dataset/examples/_heart_uci.py
declearn/dataset/examples/_mnist.py
declearn/dataset/tensorflow/__init__.py
declearn/dataset/tensorflow/_tensorflow.py
declearn/dataset/torch/__init__.py
declearn/dataset/torch/_torch.py
declearn/dataset/torch/_utils.py
declearn/dataset/utils/__init__.py
declearn/dataset/utils/_save_load.py
declearn/dataset/utils/_sparse.py
declearn/dataset/utils/_split_classif.py
declearn/fairness/__init__.py
declearn/fairness/api/__init__.py
declearn/fairness/api/_client.py
declearn/fairness/api/_dataset.py
declearn-2.7.0.dist-info/licenses/AUTHORS
declearn-2.7.0.dist-info/licenses/LICENSE
declearn-2.7.0.dist-info/METADATA
declearn-2.7.0.dist-info/WHEEL
declearn-2.7.0.dist-info/entry_points.txt
declearn-2.7.0.dist-info/top_level.txt
declearn-2.7.0.dist-info/RECORD
