Metadata-Version: 2.4
Name: declearn
Version: 2.7.0
Summary: A modular and extensible framework for Federated Learning.
Author-email: Paul Andrey <paul.andrey@inria.fr>, Nathan Bigaud <nathan.bigaud@inria.fr>, Simon Decomble <simon.decomble@inria.fr>
Maintainer-email: Paul Andrey <paul.andrey@inria.fr>, Simon Decomble <simon.decomble@inria.fr>
License:                                  Apache License
Project-URL: homepage, https://magnet.gitlabpages.inria.fr/declearn/docs
Project-URL: repository, https://gitlab.inria.fr/magnet/declearn/declearn2.git
Classifier: Development Status :: 5 - Production/Stable
Classifier: Intended Audience :: Science/Research
Classifier: License :: OSI Approved :: Apache Software License
Classifier: Operating System :: Unix
Classifier: Programming Language :: Python :: 3
Classifier: Programming Language :: Python :: 3.11
Classifier: Programming Language :: Python :: 3.12
Classifier: Programming Language :: Python :: 3.13
Classifier: Topic :: Scientific/Engineering :: Artificial Intelligence
Classifier: Topic :: Scientific/Engineering :: Mathematics
Classifier: Typing :: Typed
Requires-Python: >=3.11
License-File: LICENSE
License-File: AUTHORS
Requires-Dist: cryptography>=35.0
Requires-Dist: fire~=0.4
Requires-Dist: gmpy2~=2.1
Requires-Dist: pandas<3.0,>=1.2
Requires-Dist: requests~=2.18
Requires-Dist: scikit-learn~=1.6
Requires-Dist: tqdm~=4.62
Provides-Extra: all
Requires-Dist: dm-haiku>=0.0.15; extra == "all"
Requires-Dist: flax~=0.12; extra == "all"
Requires-Dist: grpcio>=1.45; extra == "all"
Requires-Dist: jax[cpu]~=0.8; extra == "all"
Requires-Dist: opacus~=1.4; extra == "all"
Requires-Dist: protobuf>=3.19; extra == "all"
Requires-Dist: tensorflow~=2.12; extra == "all"
Requires-Dist: torch~=2.0; extra == "all"
Requires-Dist: websockets<14.0,>=10.1; extra == "all"
Provides-Extra: dp
Requires-Dist: opacus~=1.4; extra == "dp"
Provides-Extra: grpc
Requires-Dist: grpcio>=1.45; extra == "grpc"
Requires-Dist: protobuf>=3.19; extra == "grpc"
Provides-Extra: haiku
Requires-Dist: dm-haiku>=0.0.15; extra == "haiku"
Requires-Dist: jax[cpu]~=0.8; extra == "haiku"
Requires-Dist: flax~=0.12; extra == "haiku"
Provides-Extra: tensorflow
Requires-Dist: tensorflow~=2.12; extra == "tensorflow"
Provides-Extra: torch
Requires-Dist: torch~=2.0; extra == "torch"
Provides-Extra: websockets
Requires-Dist: websockets<14.0,>=10.1; extra == "websockets"
Provides-Extra: nlp
Requires-Dist: datasets~=4.0; extra == "nlp"
Requires-Dist: transformers~=4.57; extra == "nlp"
Provides-Extra: docs
Requires-Dist: griffe~=1.0; extra == "docs"
Requires-Dist: mkdocstrings[python]~=0.8; extra == "docs"
Requires-Dist: mkdocs-autorefs~=0.4; extra == "docs"
Requires-Dist: mkdocs-literate-nav~=0.4; extra == "docs"
Requires-Dist: mkdocs-material~=9.1; extra == "docs"
Provides-Extra: tests
Requires-Dist: mypy~=1.0; extra == "tests"
Requires-Dist: pytest~=8.4; extra == "tests"
Requires-Dist: pytest-asyncio~=1.2; extra == "tests"
Requires-Dist: pytest-cov~=7.0; extra == "tests"
Requires-Dist: ruff~=0.14; extra == "tests"
Requires-Dist: tox~=4.31; extra == "tests"
Provides-Extra: dev
Requires-Dist: build>=1.3.0; extra == "dev"
Requires-Dist: griffe~=1.0; extra == "dev"
Requires-Dist: mkdocstrings[python]~=0.8; extra == "dev"
Requires-Dist: mkdocs-autorefs~=0.4; extra == "dev"
Requires-Dist: mkdocs-literate-nav~=0.4; extra == "dev"
Requires-Dist: mkdocs-material~=9.1; extra == "dev"
Requires-Dist: mypy~=1.0; extra == "dev"
Requires-Dist: pre-commit>=4.3; extra == "dev"
Requires-Dist: pytest~=8.4; extra == "dev"
Requires-Dist: pytest-asyncio~=1.2; extra == "dev"
Requires-Dist: pytest-cov~=7.0; extra == "dev"
Requires-Dist: ruff~=0.14; extra == "dev"
Requires-Dist: tox~=4.31; extra == "dev"
Dynamic: license-file
